Workbook

Sheet Overview
B2: RioDent MVP - QA Test Plan v2
B3: Updated for: Google-first sign-up, no phone OTP, no images, Hyderabad-only address, time slots, doctor-closes-with-amount, cancel reasons, admin dashboard, 1 lakh scale, Firebase prod release.
B5: Execution dashboard (updates from the Status column in 'Test Cases')
B6: Module | C6: Total | D6: Pass | E6: Fail | F6: Blocked | G6: Not Run | H6: % Pass
B7: Auth - Doctor | C7: =COUNTIF('Test Cases'!$B:$B,B7) -> 24 | D7: =COUNTIFS('Test Cases'!$B:$B,$B7,'Test Cases'!$L:$L,"Pass") -> 0 | E7: =COUNTIFS('Test Cases'!$B:$B,$B7,'Test Cases'!$L:$L,"Fail") -> 0 | F7: =COUNTIFS('Test Cases'!$B:$B,$B7,'Test Cases'!$L:$L,"Blocked") -> 0 | G7: =COUNTIFS('Test Cases'!$B:$B,$B7,'Test Cases'!$L:$L,"Not Run") -> 24 | H7: =IF(C7=0,0,D7/C7) -> 0
B8: Auth - Admin | C8: =COUNTIF('Test Cases'!$B:$B,B8) -> 11 | D8: =COUNTIFS('Test Cases'!$B:$B,$B8,'Test Cases'!$L:$L,"Pass") -> 0 | E8: =COUNTIFS('Test Cases'!$B:$B,$B8,'Test Cases'!$L:$L,"Fail") -> 0 | F8: =COUNTIFS('Test Cases'!$B:$B,$B8,'Test Cases'!$L:$L,"Blocked") -> 0 | G8: =COUNTIFS('Test Cases'!$B:$B,$B8,'Test Cases'!$L:$L,"Not Run") -> 11 | H8: =IF(C8=0,0,D8/C8) -> 0
B9: Profile | C9: =COUNTIF('Test Cases'!$B:$B,B9) -> 6 | D9: =COUNTIFS('Test Cases'!$B:$B,$B9,'Test Cases'!$L:$L,"Pass") -> 0 | E9: =COUNTIFS('Test Cases'!$B:$B,$B9,'Test Cases'!$L:$L,"Fail") -> 0 | F9: =COUNTIFS('Test Cases'!$B:$B,$B9,'Test Cases'!$L:$L,"Blocked") -> 0 | G9: =COUNTIFS('Test Cases'!$B:$B,$B9,'Test Cases'!$L:$L,"Not Run") -> 6 | H9: =IF(C9=0,0,D9/C9) -> 0
B10: Doctor - Home | C10: =COUNTIF('Test Cases'!$B:$B,B10) -> 10 | D10: =COUNTIFS('Test Cases'!$B:$B,$B10,'Test Cases'!$L:$L,"Pass") -> 0 | E10: =COUNTIFS('Test Cases'!$B:$B,$B10,'Test Cases'!$L:$L,"Fail") -> 0 | F10: =COUNTIFS('Test Cases'!$B:$B,$B10,'Test Cases'!$L:$L,"Blocked") -> 0 | G10: =COUNTIFS('Test Cases'!$B:$B,$B10,'Test Cases'!$L:$L,"Not Run") -> 10 | H10: =IF(C10=0,0,D10/C10) -> 0
B11: Doctor - Booking | C11: =COUNTIF('Test Cases'!$B:$B,B11) -> 35 | D11: =COUNTIFS('Test Cases'!$B:$B,$B11,'Test Cases'!$L:$L,"Pass") -> 0 | E11: =COUNTIFS('Test Cases'!$B:$B,$B11,'Test Cases'!$L:$L,"Fail") -> 0 | F11: =COUNTIFS('Test Cases'!$B:$B,$B11,'Test Cases'!$L:$L,"Blocked") -> 0 | G11: =COUNTIFS('Test Cases'!$B:$B,$B11,'Test Cases'!$L:$L,"Not Run") -> 35 | H11: =IF(C11=0,0,D11/C11) -> 0
B12: Time Slots | C12: =COUNTIF('Test Cases'!$B:$B,B12) -> 13 | D12: =COUNTIFS('Test Cases'!$B:$B,$B12,'Test Cases'!$L:$L,"Pass") -> 0 | E12: =COUNTIFS('Test Cases'!$B:$B,$B12,'Test Cases'!$L:$L,"Fail") -> 0 | F12: =COUNTIFS('Test Cases'!$B:$B,$B12,'Test Cases'!$L:$L,"Blocked") -> 0 | G12: =COUNTIFS('Test Cases'!$B:$B,$B12,'Test Cases'!$L:$L,"Not Run") -> 13 | H12: =IF(C12=0,0,D12/C12) -> 0
B13: Doctor - Requests | C13: =COUNTIF('Test Cases'!$B:$B,B13) -> 17 | D13: =COUNTIFS('Test Cases'!$B:$B,$B13,'Test Cases'!$L:$L,"Pass") -> 0 | E13: =COUNTIFS('Test Cases'!$B:$B,$B13,'Test Cases'!$L:$L,"Fail") -> 0 | F13: =COUNTIFS('Test Cases'!$B:$B,$B13,'Test Cases'!$L:$L,"Blocked") -> 0 | G13: =COUNTIFS('Test Cases'!$B:$B,$B13,'Test Cases'!$L:$L,"Not Run") -> 17 | H13: =IF(C13=0,0,D13/C13) -> 0
B14: Admin - Bookings | C14: =COUNTIF('Test Cases'!$B:$B,B14) -> 21 | D14: =COUNTIFS('Test Cases'!$B:$B,$B14,'Test Cases'!$L:$L,"Pass") -> 0 | E14: =COUNTIFS('Test Cases'!$B:$B,$B14,'Test Cases'!$L:$L,"Fail") -> 0 | F14: =COUNTIFS('Test Cases'!$B:$B,$B14,'Test Cases'!$L:$L,"Blocked") -> 0 | G14: =COUNTIFS('Test Cases'!$B:$B,$B14,'Test Cases'!$L:$L,"Not Run") -> 21 | H14: =IF(C14=0,0,D14/C14) -> 0
B15: Admin - Dashboard | C15: =COUNTIF('Test Cases'!$B:$B,B15) -> 10 | D15: =COUNTIFS('Test Cases'!$B:$B,$B15,'Test Cases'!$L:$L,"Pass") -> 0 | E15: =COUNTIFS('Test Cases'!$B:$B,$B15,'Test Cases'!$L:$L,"Fail") -> 0 | F15: =COUNTIFS('Test Cases'!$B:$B,$B15,'Test Cases'!$L:$L,"Blocked") -> 0 | G15: =COUNTIFS('Test Cases'!$B:$B,$B15,'Test Cases'!$L:$L,"Not Run") -> 10 | H15: =IF(C15=0,0,D15/C15) -> 0
B16: Admin - Doctors, Technicians, Settings | C16: =COUNTIF('Test Cases'!$B:$B,B16) -> 9 | D16: =COUNTIFS('Test Cases'!$B:$B,$B16,'Test Cases'!$L:$L,"Pass") -> 0 | E16: =COUNTIFS('Test Cases'!$B:$B,$B16,'Test Cases'!$L:$L,"Fail") -> 0 | F16: =COUNTIFS('Test Cases'!$B:$B,$B16,'Test Cases'!$L:$L,"Blocked") -> 0 | G16: =COUNTIFS('Test Cases'!$B:$B,$B16,'Test Cases'!$L:$L,"Not Run") -> 9 | H16: =IF(C16=0,0,D16/C16) -> 0
B17: End-to-End | C17: =COUNTIF('Test Cases'!$B:$B,B17) -> 10 | D17: =COUNTIFS('Test Cases'!$B:$B,$B17,'Test Cases'!$L:$L,"Pass") -> 0 | E17: =COUNTIFS('Test Cases'!$B:$B,$B17,'Test Cases'!$L:$L,"Fail") -> 0 | F17: =COUNTIFS('Test Cases'!$B:$B,$B17,'Test Cases'!$L:$L,"Blocked") -> 0 | G17: =COUNTIFS('Test Cases'!$B:$B,$B17,'Test Cases'!$L:$L,"Not Run") -> 10 | H17: =IF(C17=0,0,D17/C17) -> 0
B18: UI Quality | C18: =COUNTIF('Test Cases'!$B:$B,B18) -> 9 | D18: =COUNTIFS('Test Cases'!$B:$B,$B18,'Test Cases'!$L:$L,"Pass") -> 0 | E18: =COUNTIFS('Test Cases'!$B:$B,$B18,'Test Cases'!$L:$L,"Fail") -> 0 | F18: =COUNTIFS('Test Cases'!$B:$B,$B18,'Test Cases'!$L:$L,"Blocked") -> 0 | G18: =COUNTIFS('Test Cases'!$B:$B,$B18,'Test Cases'!$L:$L,"Not Run") -> 9 | H18: =IF(C18=0,0,D18/C18) -> 0
... B23: Play Store & Privacy | C23: =COUNTIF('Test Cases'!$B:$B,B23) -> 24 | D23: =COUNTIFS('Test Cases'!$B:$B,$B23,'Test Cases'!$L:$L,"Pass") -> 0 | E23: =COUNTIFS('Test Cases'!$B:$B,$B23,'Test Cases'!$L:$L,"Fail") -> 0 | F23: =COUNTIFS('Test Cases'!$B:$B,$B23,'Test Cases'!$L:$L,"Blocked") -> 0 | G23: =COUNTIFS('Test Cases'!$B:$B,$B23,'Test Cases'!$L:$L,"Not Run") -> 24 | H23: =IF(C23=0,0,D23/C23) -> 0
B24: TOTAL | C24: =SUM(C7:C23) -> 241 | D24: =SUM(D7:D23) -> 0 | E24: =SUM(E7:E23) -> 0 | F24: =SUM(F7:F23) -> 0 | G24: =SUM(G7:G23) -> 241 | H24: =IF(C24=0,0,D24/C24) -> 0
B26: Smoke cases (run after every change) | C26: =COUNTIF('Test Cases'!$E:$E,"Smoke") -> 89
B27: P0 cases not yet passed | C27: =COUNTIFS('Test Cases'!$D:$D,"P0",'Test Cases'!$L:$L,"<>Pass") -> 104
B29: Release gate: all P0 = Pass, all Smoke + Regression = Pass, no open Critical/High issue.
B30: Priority: P0 blocker, P1 important, P2 nice-to-have. Suite: Smoke = quick check after every change, Regression = full run before release.
B31: Fill 'Actual Result' and 'Status' (dropdown) while testing. Statuses: Not Run, Pass, Fail, Blocked.

Sheet Test Cases
A1: ID | B1: Module | C1: Type | D1: Priority | E1: Suite | F1: Test Case | G1: Steps | H1: Expected Result | I1: Actual Result | J1: Notes | K1: Bug / Ref | L1: Status
A2: AUTH-01 | B2: Auth - Doctor | C2: Positive | D2: P0 | E2: Smoke | F2: Google sign-up (new doctor) lands on Home | G2: 1. Fresh install 2. Tap Continue with Google 3. Pick a new Google account | H2: Account created; goes straight to Home (no profile-setup screen); name from Google shown | L2: Not Run
A3: AUTH-02 | B3: Auth - Doctor | C3: Positive | D3: P0 | E3: Smoke | F3: Google sign-in (returning doctor) opens same account | G3: 1. Sign out 2. Continue with Google using same account | H3: Same uid, same requests and profile as before | L3: Not Run
A4: AUTH-03 | B4: Auth - Doctor | C4: Negative | D4: P2 | E4: Regression | F4: Google picker cancelled | G4: 1. Tap Continue with Google 2. Dismiss picker | H4: Back on login, no error loop, button works again | L4: Not Run
A5: AUTH-04 | B5: Auth - Doctor | C5: Negative | D5: P1 | E5: Regression | F5: Google sign-in with no internet | G5: 1. Airplane mode 2. Tap Continue with Google | H5: Friendly 'no internet' message; no crash | L5: Not Run
A6: AUTH-05 | B6: Auth - Doctor | C6: Positive | D6: P0 | E6: Smoke | F6: Email registration goes straight to Home | G6: 1. Register tab: name, clinic, email, password(6+) 2. Tap Register | H6: Account created; opens Home directly | L6: Not Run
A7: AUTH-06 | B7: Auth - Doctor | C7: Negative | D7: P1 | E7: Regression | F7: Register with empty name / clinic / email / password | G7: Submit each field empty in turn | H7: Inline 'is required' error for each; nothing created | L7: Not Run
A8: AUTH-07 | B8: Auth - Doctor | C8: Negative | D8: P1 | E8: Regression | F8: Invalid email formats rejected | G8: Try: abc, abc@, abc@com, @x.com, a b@c.com | H8: 'Enter a valid email address' | L8: Not Run
A9: AUTH-08 | B9: Auth - Doctor | C9: Edge | D9: P1 | E9: Regression | F9: Valid email with long ending accepted | G9: Register with doctor@smilecare.dental, x@clinic.health, y@dr.clinic | H9: All accepted (old rule allowed only 2-4 letters) | L9: Not Run
A10: AUTH-09 | B10: Auth - Doctor | C10: Negative | D10: P1 | E10: Regression | F10: Password shorter than 6 rejected; exactly 6 accepted | G10: Try 'abc12' then 'abc123' | H10: 5 chars rejected with message; 6 chars accepted | L10: Not Run
A11: AUTH-10 | B11: Auth - Doctor | C11: Negative | D11: P0 | E11: Smoke | F11: Register with an existing email | G11: Register again with a used email | H11: 'An account already exists... switch to Sign In' | L11: Not Run
A12: AUTH-11 | B12: Auth - Doctor | C12: Positive | D12: P0 | E12: Smoke | F12: Email sign-in with valid credentials | G12: Sign in with registered email + password | H12: Opens Home with correct data | L12: Not Run
A13: AUTH-12 | B13: Auth - Doctor | C13: Negative | D13: P0 | E13: Smoke | F13: Wrong password | G13: Sign in with wrong password | H13: 'Incorrect email or password' ; stays on login | L13: Not Run
... A242: PLAY-24 | B242: Play Store & Privacy | C242: Security | D242: P1 | E242: Regression | F242: Admin account protection | G242: Check admin Gmail | H242: 2-step verification on; only 1-2 admins | L242: Not Run

Sheet Issues & Changes
A1: # | B1: Severity | C1: Reported / found | D1: Cause found in the APK | E1: Required change | F1: Test IDs
A2: I1 | B2: Critical | C2: Hard-coded admin and demo credentials; 1-Click Admin / Doctor login; Fill Test OTP; client-side admin account creation | D2: Constants and login-screen code inside the app (unchanged in both APKs) | E2: Remove all of it; rotate passwords; admin by Firebase custom claim set by a script | F2: AUTH-23, ADA-11, SEC-01, SEC-02, SEC-03
A3: I2 | B3: Critical | C3: Production rules not verified; role is stored in a user document | D3: APK cannot show the rules | E3: Deny-by-default Firestore/Storage rules; rules unit tests; enforce status transitions server-side | F3: SEC-03 to SEC-10, SEC-14, ADM-16
A4: I3 | B4: High | C4: Home dropdown tabs (Dental Chair ... Suction Pipe) show red error 'exactly one item with DropdownButton value' | D4: Dropdown built from config list with initialValue; tile names differ from config names; list can have duplicates/empty/changes; tiles open booking without category | E4: One category list with codes; de-duplicate; reset invalid selection; tiles preselect by code | F4: BKG-01 to BKG-04, HOME-05
A5: I4 | B5: High | C5: Active lead card does not show all requests; History opens same screen | D5: Home shows only active.first; app-bar icon and History both push the list with filter All | E5: Status tiles + all active requests; deep link to filtered list | F5: HOME-01 to HOME-04, DR-01
A6: I5 | B6: High | C6: Yellow-black overflow stripes (26 px etc.) on register, home, review, admin dashboard | D6: Fixed layouts without scroll or flexible widgets | E6: Make all screens scrollable/flexible; add overflow test at 3 sizes | F6: UI-01 to UI-04, AUTH-24, HOME-09, BKG-29, DSH-10
A7: I6 | B7: High | C7: 'Use GPS' cannot work on Android | D7: Manifest has no ACCESS_FINE/COARSE_LOCATION | E7: Add permissions; use free device geocoder to fill address; no paid Maps/Places API | F7: BKG-20 to BKG-26
A8: I7 | B8: High | C8: Description must be 10+ characters | D8: Validators.description | E8: Any words, 1-500 chars | F8: BKG-05 to BKG-08
A9: I8 | B9: High | C9: Images/videos cost storage | D9: Photo/video config, models, Storage code | E9: Remove everything; Storage rules deny all | F9: BKG-09, SEC-10
A10: I9 | B10: High | C10: Address: Hyderabad only; landmark, pincode; mobile mandatory; auto-fill by location | D10: Address is a single free-text; no pincode or mobile check | E10: Structured address, pincode prefix check, mandatory mobile, Detect my location | F10: BKG-11 to BKG-26
A11: I10 | B11: High | C11: Login: remove OTP and Admin Portal; Google preferred; direct to Home after register; same account every time | D11: Phone OTP tab, admin link, profile-setup gate | E11: One login screen, Google first, no profile gate, persistent session | F11: AUTH-01 to AUTH-24
A12: I11 | B12: High | C12: Admin sign-in by admin email only; remember me; change password | D12: Separate admin login with fixed credentials | E12: Same login; admin claim routes to /admin; change password via Gmail link | F12: ADA-01 to ADA-10
... A23: I21 | B23: Medium | C23: Missing for store launch: account deletion, privacy policy, support number, crash reporting | D23: Not present | E23: Add Profile screen, links, Crashlytics, Remote Config min version | F23: PRF-01, PRF-05, PRF-06, DEP-08, DEP-09
A25: Causes come from reading the APK's embedded code and manifest; both uploaded APKs contain the same code. Confirm each on a running build.
